{
  "schedule": [
    {
      "id": "fishing_tournament",
      "type": "blue_event",
      "title": {
        "zh": "釣魚大賽",
        "en": "Fishing Tournament",
        "ko": "낚시 대회",
        "ru": "Рыболовный турнир",
        "ar": "مسابقة الصيد"
      },
      "note": {
        "zh": "投入刺激的冬季釣魚世界！",
        "en": "Dive into the exciting world of winter fishing!",
        "ko": "짜릿한 겨울 낚시의 세계로!",
        "ru": "Ворвитесь в захватывающий мир зимней рыбалки!",
        "ar": "انغمس في عالم الصيد الشتوي المثير!"
      },
      "window": { "start": "2025-11-11T00:00:00Z", "end": "2025-11-14T00:00:00Z" }
    },
    {
      "id": "tundra_exchange_station",
      "type": "green_trade",
      "title": {
        "zh": "雪原交易站",
        "en": "Tundra Exchange Station",
        "ko": "설원 거래소",
        "ru": "Станция обмена «Тундра»",
        "ar": "محطة تداول الحقل الثلجي"
      },
      "note": {
        "zh": "把不需要的物品兌換成珍貴寶藏。",
        "en": "Trade unwanted items for valuable treasures.",
        "ko": "불필요한 아이템을 귀한 보물로 교환하세요.",
        "ru": "Обменивайте ненужные предметы на ценные сокровища.",
        "ar": "استبدل العناصر غير المرغوبة بكنوز قيّمة."
      },
      "window": { "start": "2025-11-10T00:00:00Z", "end": "2025-11-12T00:00:00Z" }
    },
    {
      "id": "heroic_raid",
      "type": "purple_path",
      "title": {
        "zh": "英雄遠征",
        "en": "Heroic Raid",
        "ko": "영웅 원정",
        "ru": "Героический рейд",
        "ar": "حشد الأبطال"
      },
      "note": {
        "zh": "完成每日任務以獲得路徑點數並解鎖更多獎勵。",
        "en": "Complete daily missions to earn Path points and unlock more rewards.",
        "ko": "일일 임무를 완료하여 포인트를 모으고 보상을 받으세요.",
        "ru": "Выполняйте ежедневные задания, чтобы зарабатывать очки Пути и открывать награды.",
        "ar": "أكمل المهام اليومية للحصول على نقاط المسار والمزيد من المكافآت."
      },
      "window": { "start": "2025-11-03T00:00:00Z", "end": "2025-11-17T00:00:00Z" }
    },
    {
      "id": "alliance_mobilization",
      "type": "blue_battle",
      "title": {
        "zh": "聯盟總動員",
        "en": "Alliance Mobilization",
        "ko": "연맹 총동원",
        "ru": "Мобилизация альянса",
        "ar": "تعبئة التحالف"
      },
      "note": {
        "zh": "提高聯盟評級以獲得更豐厚的獎勵。",
        "en": "Raise your alliance rating to get richer rewards.",
        "ko": "연맹 평점을 올려 더 많은 보상을 받으세요.",
        "ru": "Повышайте рейтинг альянса, чтобы получать больше наград.",
        "ar": "ارفع تصنيف تحالفك للحصول على مكافآت أكثر وفرة."
      },
      "window": { "start": "2025-11-10T00:00:00Z", "end": "2025-11-16T00:00:00Z" }
    },
    {
      "id": "overtime_work",
      "type": "brown_growth",
      "title": {
        "zh": "加班施工",
        "en": "Overtime Work",
        "ko": "철야 근무",
        "ru": "Сверхурочная работа",
        "ar": "العمل الإضافي"
      },
      "note": {
        "zh": "加速建設，犧牲一些休息時間以換取進步。",
        "en": "Accelerate construction by sacrificing some rest time.",
        "ko": "건설을 가속하려면 약간의 휴식을 포기해야 합니다.",
        "ru": "Чтобы ускорить строительство, придется пожертвовать отдыхом.",
        "ar": "لتسريع البناء، عليك التضحية ببعض وقت الراحة."
      },
      "window": { "start": "2025-11-10T00:00:00Z", "end": "2025-11-12T00:00:00Z" }
    },
    {
      "id": "battle_for_foundry",
      "type": "red_pvp",
      "title": {
        "zh": "兵工廠爭奪戰",
        "en": "Battle for the Foundry",
        "ko": "무기공장 쟁탈전",
        "ru": "Битва за литейную",
        "ar": "معركة مسبك الأسلحة"
      },
      "note": {
        "zh": "掌控兵器者方能掌控凍土。",
        "en": "Control the weapons, control the tundra.",
        "ko": "무기를 지배하는 자가 설원을 지배한다!",
        "ru": "Контроль над вооружением — это власть над тундрой.",
        "ar": "من يسيطر على الأسلحة يسيطر على الحقل الثلجي."
      },
      "window": { "start": "2025-11-10T00:00:00Z", "end": "2025-11-17T00:00:00Z" }
    },
    {
      "id": "mercenary_prestige",
      "type": "yellow_merc",
      "title": {
        "zh": "傭兵榮耀",
        "en": "Mercenary Prestige",
        "ko": "용병의 영광",
        "ru": "Слава наёмников",
        "ar": "مجد المرتزقة"
      },
      "note": {
        "zh": "勇氣與賞金並重的傭兵挑戰。",
        "en": "Mercenary challenges where courage meets bounty.",
        "ko": "용기와 보상이 함께하는 용병 도전.",
        "ru": "Испытание наёмников, где смелость встречается с наградой.",
        "ar": "تحديات المرتزقة حيث الشجاعة تقابل المكافأة."
      },
      "window": { "start": "2025-11-08T00:00:00Z", "end": "2025-11-11T00:00:00Z" }
    },
    {
      "id": "alliance_championship",
      "type": "blue_battle",
      "title": {
        "zh": "聯盟錦標賽",
        "en": "Alliance Championship",
        "ko": "연맹 챔피언십",
        "ru": "Чемпионат альянса",
        "ar": "بطولة التحالف"
      },
      "note": {
        "zh": "與盟友攜手爭奪榮耀。",
        "en": "Earn glory together with your allies.",
        "ko": "동맹과 함께 영광을 쟁취하세요.",
        "ru": "Зарабатывайте славу вместе с союзниками.",
        "ar": "اربح المجد مع حلفائك."
      },
      "window": { "start": "2025-11-10T00:00:00Z", "end": "2025-11-17T00:00:00Z" }
    },
    {
      "id": "fortress_battle",
      "type": "red_pvp",
      "title": {
        "zh": "堡壘爭奪戰",
        "en": "Fortress Battle",
        "ko": "요새 전투",
        "ru": "Битва за форт",
        "ar": "معركة الحصن"
      },
      "note": {
        "zh": "與盟友並肩作戰，奪取堡壘，名留榮耀之牆！",
        "en": "Fight alongside allies, capture fortresses, and earn eternal glory.",
        "ko": "동맹과 함께 요새를 점령하고 명예를 쟁취하세요!",
        "ru": "Сражайтесь бок о бок с союзниками и захватывайте форты!",
        "ar": "قاتل جنبًا إلى جنب مع حلفائك واستولِ على الحصون!"
      },
      "window": { "start": "2025-11-11T00:00:00Z", "end": "2025-11-15T00:00:00Z" }
    },
    {
      "id": "prepare_for_war",
      "type": "brown_growth",
      "title": {
        "zh": "戰備整軍",
        "en": "Preparation for War",
        "ko": "전쟁 준비",
        "ru": "Подготовка к войне",
        "ar": "التحضير للحرب"
      },
      "note": {
        "zh": "英雄需要更強的裝備與更多部隊！",
        "en": "Heroes need stronger gear and more troops!",
        "ko": "영웅에게는 더 강한 장비와 더 많은 병력이 필요합니다!",
        "ru": "Героям нужно более мощное снаряжение и больше войск!",
        "ar": "الأبطال بحاجة إلى عتاد أقوى ومزيد من القوات!"
      },
      "window": { "start": "2025-11-12T00:00:00Z", "end": "2025-11-14T00:00:00Z" }
    },
    {
      "id": "ginas_revenge",
      "type": "yellow_merc",
      "title": {
        "zh": "吉娜的復仇",
        "en": "Gina’s Revenge",
        "ko": "지나의 복수",
        "ru": "Месть Джины",
        "ar": "انتقام جينا"
      },
      "note": {
        "zh": "協助傭兵首領吉娜追獵失控的怪物，讓她加入你的城市。",
        "en": "Help mercenary leader Gina hunt the Uncontrolled cryptid so she can join your city.",
        "ko": "용병 대장 지나가 통제 불능의 괴수를 추적하도록 도와주세요.",
        "ru": "Помогите Джине выследить неконтролируемого криптида, чтобы нанять её в город.",
        "ar": "ساعد زعيمة المرتزقة جينا في مطاردة الوحش غير المنضبط لتجنيدها في مدينتك."
      },
      "window": { "start": "2025-11-12T00:00:00Z", "end": "2025-11-15T00:00:00Z" }
    },
    {
      "id": "snowfield_trade_route",
      "type": "green_trade",
      "title": {
        "zh": "雪原商道",
        "en": "Snowfield Trade Route",
        "ko": "설원 장삿길",
        "ru": "Торговый путь в тундре",
        "ar": "طريق تجارة الحقل الثلجي"
      },
      "note": {
        "zh": "危機四伏的商道，護送與掠奪者爭奪主導權。",
        "en": "A perilous trade route where escorts and raiders vie for control.",
        "ko": "위험천만한 장삿길에서 호송대와 약탈자가 패권을 다툽니다.",
        "ru": "Опасный торговый путь, где караваны и рейдеры борются за власть.",
        "ar": "طريق تجاري محفوف بالمخاطر يتنافس فيه المرافقون والمغيرون على الهيمنة."
      },
      "window": { "start": "2025-11-13T00:00:00Z", "end": "2025-11-16T04:00:00Z" }
    },
    {
      "id": "city_development",
      "type": "brown_growth",
      "title": {
        "zh": "城市發展",
        "en": "City Development",
        "ko": "도시 발전",
        "ru": "Развитие города",
        "ar": "تطوير المدينة"
      },
      "note": {
        "zh": "帶領倖存者建造全新的家園。",
        "en": "Lead the survivors and build a new home.",
        "ko": "생존자들을 이끌고 새로운 보금자리를 만드세요.",
        "ru": "Возглавьте выживших и постройте новый дом.",
        "ar": "قُد الناجين وابنِ منزلًا جديدًا."
      },
      "window": { "start": "2025-11-14T00:00:00Z", "end": "2025-11-16T00:00:00Z" }
    }
  ]
}


